[["If `n : ℕ+` is different from `1`, then it is the successor of some `k : ℕ+`. ",{"type":"∀ {n : ℕ+}, n ≠ 1 → ∃ k, n = k + 1","name":"PNat.exists_eq_succ_of_ne_one","isProp":true,"docString":"If `n : ℕ+` is different from `1`, then it is the successor of some `k : ℕ+`. ","distance":0.6546838435755015783712451593601144850254058837890625}],[" For all natural numbers `n`, the product of `n` and `n-1` is an even number. Equivalently, the product of two consecutive natural numbers is an even number.",{"type":"∀ (n : ℕ), Even (n * (n - 1))","name":"Nat.even_mul_self_pred","isProp":true,"docString":" For all natural numbers `n`, the product of `n` and `n-1` is an even number. Equivalently, the product of two consecutive natural numbers is an even number.","distance":0.58281774852805146025502835982479155063629150390625}],["This theorem states that for any natural numbers `n` and `k`, the product of `n` and the ascending factorial of `n+1` and `k` equals the product of `n+k` and the ascending factorial of `n` and `k`. Here, the ascending factorial `Nat.ascFactorial n k` is defined as the product `n * (n + 1) * ... * (n + k - 1)`.",{"type":"∀ (n k : ℕ), n * n.succ.ascFactorial k = (n + k) * n.ascFactorial k","name":"Nat.succ_ascFactorial","isProp":true,"docString":"This theorem states that for any natural numbers `n` and `k`, the product of `n` and the ascending factorial of `n+1` and `k` equals the product of `n+k` and the ascending factorial of `n` and `k`. Here, the ascending factorial `Nat.ascFactorial n k` is defined as the product `n * (n + 1) * ... * (n + k - 1)`.","distance":0.66352259541905811435213990989723242819309234619140625}],["Equivalence between the set of natural numbers which are `≥ k` and `ℕ`, given by `n → n - k`. ",{"type":"(k : ℕ) → { n // n ∉ Multiset.range k } ≃ ℕ","name":"notMemRangeEquiv","isProp":false,"docString":"Equivalence between the set of natural numbers which are `≥ k` and `ℕ`, given by `n → n - k`. ","distance":0.77186930586762081407670166299794800579547882080078125}],[" For any natural numbers `n` and `k` with `n > 0`, the product of `(n - 1)!` and `k` ascending factorials of `n` is equal to `(n + k - 1)!`.",{"type":"∀ (n k : ℕ), 0 < n → (n - 1).factorial * n.ascFactorial k = (n + k - 1).factorial","name":"Nat.factorial_mul_ascFactorial'","isProp":true,"docString":" For any natural numbers `n` and `k` with `n > 0`, the product of `(n - 1)!` and `k` ascending factorials of `n` is equal to `(n + k - 1)!`.","distance":0.597234869423528547116575282416306436061859130859375}],["This theorem states that for all natural numbers `n`, the product of `n` and `n - 1` is an even number. In mathematical terms, this theorem can be written as: \"∀ n ∈ ℕ, n*(n - 1) is even.\" Here, a number is considered even if it can be expressed as twice another number, in this case, n*(n - 1) = 2*r for some `r`.",{"type":"∀ (n : ℕ), Even (n * (n - 1))","name":"Nat.even_mul_self_pred","isProp":true,"docString":"This theorem states that for all natural numbers `n`, the product of `n` and `n - 1` is an even number. In mathematical terms, this theorem can be written as: \"∀ n ∈ ℕ, n*(n - 1) is even.\" Here, a number is considered even if it can be expressed as twice another number, in this case, n*(n - 1) = 2*r for some `r`.","distance":0.67531582283888724749232324029435403645038604736328125}],["Multiplication by `(n + 1 : ℕ)` behaves as expected. ",{"type":"∀ {M : Type u} [self : AddMonoid M] (n : ℕ) (x : M), AddMonoid.nsmul (n + 1) x = AddMonoid.nsmul n x + x","name":"AddMonoid.nsmul_succ","isProp":true,"docString":"Multiplication by `(n + 1 : ℕ)` behaves as expected. ","distance":0.78616982087139863910607573416200466454029083251953125}],["Any nonzero natural number is the product of an odd part `m` and a power of\ntwo `2 ^ k`. ",{"type":"∀ {n : ℕ}, n ≠ 0 → ∃ k m, Odd m ∧ n = 2 ^ k * m","name":"Nat.exists_eq_two_pow_mul_odd","isProp":true,"docString":"Any nonzero natural number is the product of an odd part `m` and a power of\ntwo `2 ^ k`. ","distance":0.79980988668548158582183305043145082890987396240234375}],["For any natural `k` and a real `r > 1` we have `n ^ k = o(r ^ n)` as `n → ∞`. ",{"type":"∀ {R : Type u_2} [inst : NormedRing R] (k : ℕ) {r : ℝ}, 1 < r → (fun n => ↑n ^ k) =o[Filter.atTop] fun n => r ^ n","name":"isLittleO_pow_const_const_pow_of_one_lt","isProp":true,"docString":"For any natural `k` and a real `r > 1` we have `n ^ k = o(r ^ n)` as `n → ∞`. ","distance":0.804390283172007780621015626820735633373260498046875}],["`n` is a prime power if there is a prime `p` and a positive natural `k` such that `n` can be\nwritten as `p^k`. ",{"type":"{R : Type u_1} → [inst : CommMonoidWithZero R] → R → Prop","name":"IsPrimePow","isProp":false,"docString":"`n` is a prime power if there is a prime `p` and a positive natural `k` such that `n` can be\nwritten as `p^k`. ","distance":0.8140334697717903633673586227814666926860809326171875}],["Raising to the power `(n + 1 : ℕ)` behaves as expected. ",{"type":"∀ {α : Type u_1} [self : CanonicallyOrderedCommSemiring α] (n : ℕ) (x : α),\n  CanonicallyOrderedCommSemiring.npow (n + 1) x = CanonicallyOrderedCommSemiring.npow n x * x","name":"CanonicallyOrderedCommSemiring.npow_succ","isProp":true,"docString":"Raising to the power `(n + 1 : ℕ)` behaves as expected. ","distance":0.8363033481461255025379841754329390823841094970703125}],["An equivalent definition for prime powers: `n` is a prime power iff there is a prime `p` and a\nnatural `k` such that `n` can be written as `p^(k+1)`. ",{"type":"∀ {R : Type u_1} [inst : CommMonoidWithZero R] (n : R), IsPrimePow n ↔ ∃ p k, Prime p ∧ p ^ (k + 1) = n","name":"isPrimePow_iff_pow_succ","isProp":true,"docString":"An equivalent definition for prime powers: `n` is a prime power iff there is a prime `p` and a\nnatural `k` such that `n` can be written as `p^(k+1)`. ","distance":0.843473939210841905378401861526072025299072265625}],["A natural number `n` is a sum of two squares if and only if `n = a^2 * b` with natural\nnumbers `a` and `b` such that `-1` is a square modulo `b`. ",{"type":"∀ {n : ℕ}, (∃ x y, n = x ^ 2 + y ^ 2) ↔ ∃ a b, n = a ^ 2 * b ∧ IsSquare (-1)","name":"Nat.eq_sq_add_sq_iff_eq_sq_mul","isProp":true,"docString":"A natural number `n` is a sum of two squares if and only if `n = a^2 * b` with natural\nnumbers `a` and `b` such that `-1` is a square modulo `b`. ","distance":0.84939533767756059123854583958745934069156646728515625}],["Prime factors of `a ^ (2 ^ n) + 1` are of form `k * 2 ^ (n + 1) + 1`. ",{"type":"∀ {a n p : ℕ}, Nat.Prime p → p ≠ 2 → p ∣ a ^ 2 ^ n + 1 → ∃ k, p = k * 2 ^ (n + 1) + 1","name":"Nat.pow_pow_add_primeFactors_one_lt","isProp":true,"docString":"Prime factors of `a ^ (2 ^ n) + 1` are of form `k * 2 ^ (n + 1) + 1`. ","distance":0.8533269841181720938294574807514436542987823486328125}],["`(n + 1).ascFactorial k = (n + k) ! / n !` but without ℕ-division. See\n`Nat.ascFactorial_eq_div` for the version with ℕ-division. ",{"type":"∀ (n k : ℕ), n.factorial * (n + 1).ascFactorial k = (n + k).factorial","name":"Nat.factorial_mul_ascFactorial","isProp":true,"docString":"`(n + 1).ascFactorial k = (n + k) ! / n !` but without ℕ-division. See\n`Nat.ascFactorial_eq_div` for the version with ℕ-division. ","distance":0.85343936359040828421029800665564835071563720703125}],["`i + k : Fin2 (n + k)` when `i : Fin2 n` and `k : ℕ` ",{"type":"{n : ℕ} → Fin2 n → (k : ℕ) → Fin2 (n + k)","name":"Fin2.add","isProp":false,"docString":"`i + k : Fin2 (n + k)` when `i : Fin2 n` and `k : ℕ` ","distance":0.8540654008500763172406777812284417450428009033203125}],["positive integers summing to `n`",{"type":"{n : ℕ} → n.Partition → Multiset ℕ","name":"Nat.Partition.parts","isProp":false,"docString":"positive integers summing to `n`","distance":0.8578120961128641308590658809407614171504974365234375}],["If `n > 0` then `m` is not divisible by `n` iff it is between `n * k` and `n * (k + 1)`\nfor some `k`. ",{"type":"∀ {n : ℤ} (m : ℤ), 0 < n → ((∃ k, n * k < m ∧ m < n * (k + 1)) ↔ ¬n ∣ m)","name":"Int.exists_lt_and_lt_iff_not_dvd","isProp":true,"docString":"If `n > 0` then `m` is not divisible by `n` iff it is between `n * k` and `n * (k + 1)`\nfor some `k`. ","distance":0.862329347559469550077437816071324050426483154296875}],["The `n`-th coefficient of the `k`-th power of a power series. ",{"type":"∀ {R : Type u_2} [inst : CommSemiring R] (k n : ℕ) (φ : PowerSeries R),\n  (PowerSeries.coeff R n) (φ ^ k) =\n    ∑ l ∈ (Finset.range k).finsuppAntidiag n, ∏ i ∈ Finset.range k, (PowerSeries.coeff R (l i)) φ","name":"PowerSeries.coeff_pow","isProp":true,"docString":"The `n`-th coefficient of the `k`-th power of a power series. ","distance":0.86369811469473589671252966581960208714008331298828125}],["If `n` is a nonzero natural number and `p ≠ 1`, then there are natural numbers `e`\nand `n'` such that `n'` is not divisible by `p` and `n = p^e * n'`. ",{"type":"∀ {n : ℕ}, n ≠ 0 → ∀ (p : ℕ), p ≠ 1 → ∃ e n', ¬p ∣ n' ∧ n = p ^ e * n'","name":"Nat.exists_eq_pow_mul_and_not_dvd","isProp":true,"docString":"If `n` is a nonzero natural number and `p ≠ 1`, then there are natural numbers `e`\nand `n'` such that `n'` is not divisible by `p` and `n = p^e * n'`. ","distance":0.865020900328840713910949489218182861804962158203125}],["The integers modulo `n : ℕ`. ",{"type":"ℕ → Type","name":"ZMod","isProp":false,"docString":"The integers modulo `n : ℕ`. ","distance":0.86896433845141130003497664802125655114650726318359375}],["If `m` and `n` are natural numbers, then the natural number `m^n` is even\nif and only if `m` is even and `n` is positive. ",{"type":"∀ {m n : ℕ}, Even (m ^ n) ↔ Even m ∧ n ≠ 0","name":"Nat.even_pow","isProp":true,"docString":"If `m` and `n` are natural numbers, then the natural number `m^n` is even\nif and only if `m` is even and `n` is positive. ","distance":0.8712330868513247228435147917480207979679107666015625}],["A single variable `n` is represented by a sum with coefficient `1` and monomial `n`. ",{"type":"ℕ → Linarith.Sum","name":"Linarith.var","isProp":false,"docString":"A single variable `n` is represented by a sum with coefficient `1` and monomial `n`. ","distance":0.87345166951467245741724809704464860260486602783203125}],["`n.ascFactorial k = (n + k - 1)! / (n - 1)!` for `n > 0` but without ℕ-division. See\n`Nat.ascFactorial_eq_div` for the version with ℕ-division. Consider using\n`factorial_mul_ascFactorial` to avoid complications of ℕ-subtraction. ",{"type":"∀ (n k : ℕ), 0 < n → (n - 1).factorial * n.ascFactorial k = (n + k - 1).factorial","name":"Nat.factorial_mul_ascFactorial'","isProp":true,"docString":"`n.ascFactorial k = (n + k - 1)! / (n - 1)!` for `n > 0` but without ℕ-division. See\n`Nat.ascFactorial_eq_div` for the version with ℕ-division. Consider using\n`factorial_mul_ascFactorial` to avoid complications of ℕ-subtraction. ","distance":0.874310655621138632653810418560169637203216552734375}]]